IPweather/IPweather.py
IPweather/__init__.py
IPweather-0.1.8.dist-info/LICENSE
IPweather-0.1.8.dist-info/METADATA
IPweather-0.1.8.dist-info/WHEEL
IPweather-0.1.8.dist-info/top_level.txt
IPweather-0.1.8.dist-info/RECORD
