Metadata-Version: 2.1
Name: IPweather
Version: 0.1.8
Summary: A package to get the current weather using a IP address or other data and to get the Ip address of the user.
Home-page: https://github.com/cookie0o/IPweather
Author: cookie0_o
Author-email: therealcookie@waifu.club
Classifier: Programming Language :: Python :: 3
Classifier: License :: OSI Approved :: MIT License
Classifier: Operating System :: OS Independent
License-File: LICENSE
